spectree/__init__.py
spectree/cli.py
spectree/core.py
spectree_md-0.1.0.dist-info/METADATA
spectree_md-0.1.0.dist-info/WHEEL
spectree_md-0.1.0.dist-info/entry_points.txt
spectree_md-0.1.0.dist-info/RECORD
