Metadata-Version: 2.4
Name: spectree-md
Version: 0.1.0
Summary: Composable Markdown trees using @ references
License-Expression: MIT
Requires-Python: >=3.10
Requires-Dist: rich
Requires-Dist: typer
Provides-Extra: dev
Requires-Dist: pytest; extra == 'dev'
Requires-Dist: ruff; extra == 'dev'
